{
    "prepare_queue": {
        "installed": [],
        "uninstalled": []
    },
    "config_munge": {
        "files": {}
    },
    "installed_plugins": {
        "cordova-plugin-ble": {
            "PACKAGE_NAME": "es.deusto.UDbeaconizer"
        },
        "cordova-plugin-eddystone": {
            "PACKAGE_NAME": "es.deusto.UDbeaconizer"
        },
        "cordova-plugin-whitelist": {
            "PACKAGE_NAME": "es.deusto.UDbeaconizer"
        }
    },
    "dependent_plugins": {},
    "modules": [
        {
            "file": "plugins/cordova-plugin-ble/ble.js",
            "id": "cordova-plugin-ble.BLE",
            "pluginId": "cordova-plugin-ble",
            "clobbers": [
                "evothings.ble"
            ]
        },
        {
            "file": "plugins/cordova-plugin-eddystone/js/eddystone-plugin.js",
            "id": "cordova-plugin-eddystone.eddystoneplugin",
            "pluginId": "cordova-plugin-eddystone",
            "clobbers": [
                "evothings.eddystone"
            ]
        }
    ],
    "plugin_metadata": {
        "cordova-plugin-ble": "1.0.1",
        "cordova-plugin-eddystone": "1.1.0",
        "cordova-plugin-whitelist": "1.2.1"
    }
}